{
  "taglines": [
    "Simplify contract management for Amazon sellers.",
    "Stay on top of renewals effortlessly.",
    "Your manual-first approach to contracts.",
    "Track supplier contracts with ease.",
    "Manual reminders for Amazon sellers."
  ],
  "hero_headlines": [
    "Manage contracts without the hassle.",
    "Never miss a renewal deadline again.",
    "A better way for Amazon sellers to track contracts.",
    "Streamline your contract workflow today.",
    "Manual tracking made simple for Amazon sellers."
  ],
  "hero_subheads": [
    "Tailored for Amazon sellers handling 10\u201320 invoices monthly.",
    "Keep your supplier contracts organized manually.",
    "Say goodbye to missed deadlines with our reminders.",
    "Effortless tracking for busy Amazon sellers.",
    "Ensure smooth contract renewals with manual alerts."
  ],
  "value_props": [
    "Manual entry for clear contract oversight.",
    "Simple tracking for Amazon sellers' contracts.",
    "Custom reminders to prevent missed deadlines.",
    "Efficient supplier onboarding for Amazon sellers.",
    "Organized contract storage tailored for sellers."
  ],
  "feature_bullets": [
    "Supplier onboarding process designed for Amazon sellers.",
    "Easy contract storage for your invoices.",
    "Renewal deadline alerts to keep you informed.",
    "Manual tracking that fits your workflow.",
    "Clear reminders for Amazon sellers on contract renewals."
  ],
  "cta_variants": [
    "Start tracking your contracts today.",
    "Get organized with our simple tool.",
    "Set up your reminders now.",
    "Join other Amazon sellers in managing contracts.",
    "Take control of your renewals."
  ]
}
