{
  "taglines": [
    "Streamline client tracking for agencies",
    "Focus on clients, not spreadsheets",
    "Effortless lead activity management",
    "Simple tracking for busy agencies",
    "Maximize revenue with clear insights"
  ],
  "hero_headlines": [
    "Transform how your agency tracks leads",
    "Say goodbye to inefficient spreadsheets",
    "Track client activities with ease",
    "Simplify revenue forecasting for your agency",
    "Weekly reports made easy for agencies"
  ],
  "hero_subheads": [
    "Manual-first workflows for marketing agencies",
    "Stay organized and informed on client activity",
    "No more missed opportunities with clear tracking",
    "Efficient lead management tailored for your agency",
    "Get actionable insights to boost your revenue"
  ],
  "value_props": [
    "Manual entry for precise lead tracking",
    "Weekly sales reports tailored for agencies",
    "Clear revenue forecasting for better planning",
    "Focused on the needs of marketing agencies",
    "Simple reminders to keep your agency on track"
  ],
  "feature_bullets": [
    "Track lead activity manually for accuracy",
    "Generate weekly sales reports effortlessly",
    "Forecast revenue based on real data",
    "Designed for agencies managing multiple clients",
    "Organize client information without hassle"
  ],
  "cta_variants": [
    "Start tracking leads today",
    "Get your agency organized now",
    "See how easy client management can be",
    "Join other agencies improving their workflows",
    "Request a demo for your agency"
  ]
}
