{
  "taglines": [
    "Track expenses easily.",
    "Simplify your expense reports.",
    "Cash flow clarity for sales teams.",
    "Timely submissions made simple.",
    "Effortless expense management."
  ],
  "hero_headlines": [
    "Sales Teams: Track Expenses with Ease.",
    "Stay on Top of Your Expense Reports.",
    "Timely Expense Reporting for Sales Teams.",
    "Efficient Expense Tracking for QuickBooks Users.",
    "Master Your Expense Reports Today."
  ],
  "hero_subheads": [
    "Manual entry made straightforward.",
    "Never miss a deadline again.",
    "Focus on sales, not paperwork.",
    "Quick and easy expense tracking.",
    "Your cash flow, organized."
  ],
  "value_props": [
    "Sales teams can submit reports on time.",
    "Manual tracking reduces cash flow gaps.",
    "User-friendly dashboard for easy tracking.",
    "Receipt scanning simplifies expense management.",
    "Monthly reports keep finances in check."
  ],
  "feature_bullets": [
    "Scan and categorize receipts effortlessly.",
    "Generate monthly reports without hassle.",
    "Dashboard tailored for sales team needs.",
    "QuickBooks integration for seamless tracking.",
    "Set reminders for timely submissions."
  ],
  "cta_variants": [
    "Start tracking your expenses now.",
    "Get started with easy expense management.",
    "Join sales teams simplifying their reporting.",
    "Sign up for timely expense tracking.",
    "Experience effortless expense reporting today."
  ]
}
