{
  "taglines": [
    "Simplify your invoice process.",
    "Precision for legal billing specialists.",
    "Effortless invoice formatting.",
    "Track invoices with ease.",
    "Manual-first, error-free invoicing."
  ],
  "hero_headlines": [
    "Streamline Invoicing for Legal Billing Specialists",
    "Say Goodbye to Invoice Formatting Errors",
    "Transform Timesheet Data into Accurate Invoices",
    "Manual Entry Made Simple for Legal Billing",
    "Ensure Cash Flow with Accurate Invoices"
  ],
  "hero_subheads": [
    "Designed for legal billing specialists handling 5-15 invoices monthly.",
    "Convert timesheet data seamlessly into formatted invoices.",
    "Manual workflows that fit your billing needs.",
    "Customizable templates for precise invoicing.",
    "Stay on top of your invoices with reminders."
  ],
  "value_props": [
    "Manual data entry tailored for legal billing specialists.",
    "Custom templates to meet your unique needs.",
    "Easily track invoice payments and status.",
    "Reminders for timely invoice submissions.",
    "Reduce cash flow gaps with accurate formatting."
  ],
  "feature_bullets": [
    "Manual data entry for precise timesheet tracking.",
    "Customizable invoice templates for legal billing.",
    "User-friendly manual invoice entry form.",
    "Reminders to keep your invoicing on schedule.",
    "Simple tracking of invoice payments."
  ],
  "cta_variants": [
    "Start your free trial today.",
    "Get started with accurate invoicing.",
    "Try our manual-first invoice tool now.",
    "Sign up for seamless invoice tracking.",
    "Experience hassle-free invoicing."
  ]
}
