{
  "taglines": [
    "Freelancers' cash flow, simplified.",
    "Track your invoices, boost your flow.",
    "Invoicing made easy for freelancers.",
    "Stay on top of your payments.",
    "Freelancers: Close the cash gap."
  ],
  "hero_headlines": [
    "Freelancers: Streamline Your Invoicing.",
    "Say Goodbye to Cash Flow Gaps.",
    "Freelancers: Keep Your Payments Flowing.",
    "Effortless Invoicing for Freelancers.",
    "Freelancers: Manage Invoices with Ease."
  ],
  "hero_subheads": [
    "Manual entry made simple for freelancers.",
    "Track outstanding invoices effortlessly.",
    "Freelancers, take control of your cash flow.",
    "Customizable templates for your unique needs.",
    "Freelancers: Simplify your invoicing process."
  ],
  "value_props": [
    "Freelancers can track invoices easily.",
    "Custom templates save freelancers time.",
    "Simple reporting for freelancers' peace of mind.",
    "Manual entry forms tailored for freelancers.",
    "Freelancers gain clarity in cash flow."
  ],
  "feature_bullets": [
    "Customizable invoice templates for freelancers.",
    "Simple reporting to track outstanding invoices.",
    "Manual invoice entry form designed for freelancers.",
    "User-friendly interface for easy navigation.",
    "Quick access to payment reminders for freelancers."
  ],
  "cta_variants": [
    "Start tracking your invoices today.",
    "Get your cash flow on track now.",
    "Try our invoicing tool for freelancers.",
    "Sign up and simplify your invoicing.",
    "Join freelancers managing cash flow better."
  ]
}
