{
  "taglines": [
    "Streamline tenant tracking for property managers.",
    "Capture leads without missing opportunities.",
    "Simplify invoicing for property managers.",
    "Effortless reminders for tenant follow-ups.",
    "Manage properties with ease and precision."
  ],
  "hero_headlines": [
    "Empower Property Managers to Capture Leads.",
    "Simplified Tracking for Property Managers.",
    "Your Essential Tool for Managing Properties.",
    "Efficiently Nurture Tenants with Ease.",
    "Transform Your Property Management Workflow."
  ],
  "hero_subheads": [
    "For property managers handling 10-20 properties.",
    "Say goodbye to missed tenant opportunities.",
    "Manual entry made simple for invoicing.",
    "Stay organized with vendor management tools.",
    "Focus on what matters: your tenants."
  ],
  "value_props": [
    "Manual entry forms for seamless invoicing.",
    "Email nurturing sequences tailored for tenants.",
    "Vendor list management for easy access.",
    "Reminders that keep you on track.",
    "Capture leads without complex processes."
  ],
  "feature_bullets": [
    "Email sequences that engage tenants effectively.",
    "Manual invoice entry for accuracy.",
    "Organized vendor list for quick reference.",
    "Custom reminders for follow-ups.",
    "Simple tracking for property managers."
  ],
  "cta_variants": [
    "Start simplifying your property management today.",
    "Capture more leads with our tool.",
    "Get started with manual tracking now.",
    "Manage your properties efficiently.",
    "Sign up for streamlined tenant management."
  ]
}
