{
  "taglines": [
    "Timely payroll for restaurant managers",
    "Simplified payroll for busy managers",
    "Effortless payroll tracking for restaurants",
    "Stay compliant with your payroll process",
    "Easy payroll management for restaurant leaders"
  ],
  "hero_headlines": [
    "Streamline Your Payroll Process Today",
    "Payroll Made Easy for Restaurant Managers",
    "Never Miss a Payroll Deadline Again",
    "Take Control of Your Payroll Management",
    "Efficient Payroll Tracking for Restaurants"
  ],
  "hero_subheads": [
    "Manual entry options for precise adjustments.",
    "Timely reminders to keep you compliant.",
    "Simplify your payroll with easy tracking.",
    "Stay on top of tax filings effortlessly.",
    "Designed for restaurant managers like you."
  ],
  "value_props": [
    "Manual entry for accurate payroll adjustments.",
    "Timely reminders for tax filing deadlines.",
    "Easy tracking for restaurant payroll needs.",
    "Simplified invoice entry for restaurant managers.",
    "Stay compliant with straightforward processes."
  ],
  "feature_bullets": [
    "Tax filing reminders tailored for managers.",
    "Manual entry options for payroll adjustments.",
    "User-friendly invoice entry form.",
    "Real-time tracking for payroll accuracy.",
    "Designed for restaurant managers processing multiple payrolls."
  ],
  "cta_variants": [
    "Get started with easy payroll tracking.",
    "Sign up for timely payroll reminders.",
    "Try our manual-first payroll tool now.",
    "Join other restaurant managers today.",
    "Experience hassle-free payroll management."
  ]
}
