{
  "taglines": [
    "Track invoices with ease.",
    "Manage vendor payments simply.",
    "Stay on top of payment schedules.",
    "Manual entry made straightforward.",
    "Reminders that keep you organized."
  ],
  "hero_headlines": [
    "Streamline your invoice tracking.",
    "Effortless vendor invoice management.",
    "Keep payment schedules in check.",
    "Simple manual workflows for law firms.",
    "Stay ahead with timely reminders."
  ],
  "hero_subheads": [
    "Perfect for law firms managing invoices.",
    "Designed for professionals needing clarity.",
    "Your manual-first approach to contract management.",
    "No more missed payments or deadlines.",
    "Easily track invoices and vendor payments."
  ],
  "value_props": [
    "Manual entry forms tailored for law firms.",
    "Easily manage vendor lists and invoices.",
    "Calculate payment schedules effortlessly.",
    "Stay organized with manual tracking.",
    "Receive reminders for upcoming payments."
  ],
  "feature_bullets": [
    "User-friendly manual invoice entry form.",
    "Comprehensive vendor list management tool.",
    "Accurate payment schedule calculator.",
    "Custom reminders for invoice due dates.",
    "Simple tracking for law firm invoices."
  ],
  "cta_variants": [
    "Start tracking invoices today.",
    "Manage your vendor payments now.",
    "Get organized with payment reminders.",
    "Simplify your invoice process.",
    "Join us for better invoice tracking."
  ]
}
