{
  "taglines": [
    "Precision for hospitality accounting teams",
    "Streamlined invoice tracking for teams",
    "Simplified workflows for accounting teams",
    "Reliable invoice matching for hospitality",
    "Empowering hospitality accounting teams"
  ],
  "hero_headlines": [
    "Match invoices accurately, every time",
    "Say goodbye to invoice discrepancies",
    "Effortless tracking for accounting teams",
    "Invoice clarity for hospitality professionals",
    "Transform your invoice management process"
  ],
  "hero_subheads": [
    "Designed for hospitality accounting teams processing 10\u201320 invoices/month",
    "Eliminate penalties with accurate matching",
    "Track vendor invoices with ease",
    "Manual entry made simple for your team",
    "Generate reports without hassle"
  ],
  "value_props": [
    "Manual invoice entry tailored for your team",
    "Discrepancy reports that keep you informed",
    "User-friendly dashboard for easy navigation",
    "Focused on hospitality accounting needs",
    "Reduce errors in invoice processing"
  ],
  "feature_bullets": [
    "Manual invoice entry for precise control",
    "Generate detailed discrepancy reports",
    "Intuitive dashboard for easy tracking",
    "Custom reminders for invoice deadlines",
    "Ideal for hospitality accounting workflows"
  ],
  "cta_variants": [
    "Start tracking invoices today",
    "Get your free trial now",
    "Join hospitality teams improving accuracy",
    "Discover manual-first invoice management",
    "Contact us for a demo"
  ]
}
