{
  "taglines": [
    "Streamline your claims workflow.",
    "Efficient tracking for busy supervisors.",
    "Stay on top of every claim.",
    "Simplify your claims management.",
    "Track claims with ease."
  ],
  "hero_headlines": [
    "Transform Your Claims Tracking.",
    "Efficiently Manage Your Claims.",
    "Say Goodbye to Tracking Delays.",
    "Simplify Your Claims Process.",
    "Stay Updated on Every Claim."
  ],
  "hero_subheads": [
    "For supervisors handling 10-20 claims monthly.",
    "Manual entry made simple for you.",
    "Compile status updates effortlessly.",
    "Never miss an important claim update.",
    "Your claims workflow, redefined for efficiency."
  ],
  "value_props": [
    "Manual entry of claim details for accuracy.",
    "Compile status updates without hassle.",
    "Receive timely email notifications.",
    "Designed for supervisors managing 10-20 claims.",
    "Eliminate delays in claim resolutions."
  ],
  "feature_bullets": [
    "Easy manual entry for every claim.",
    "Compile updates in one place.",
    "Receive notifications on claim statuses.",
    "Tailored for busy claims supervisors.",
    "Track 10-20 claims without confusion."
  ],
  "cta_variants": [
    "Start tracking your claims today.",
    "Get started with efficient tracking.",
    "Simplify your claims management now.",
    "Join fellow supervisors in streamlining claims.",
    "Take control of your claims process."
  ]
}
