{
  "taglines": [
    "Streamline your billing process.",
    "Efficient reconciliation for clinics.",
    "Simplify patient billing workflows.",
    "Manual tracking made easy.",
    "Stay on top of your invoices."
  ],
  "hero_headlines": [
    "Effortless Billing for Medical Clinics.",
    "Say Goodbye to Reconciliation Hassles.",
    "Track Invoices with Ease.",
    "Transform Your Billing Workflow.",
    "Master Your Patient Records."
  ],
  "hero_subheads": [
    "Designed for clinics processing 10-20 invoices monthly.",
    "Eliminate cash flow gaps in your practice.",
    "Manual entry support for accurate records.",
    "User-friendly interface for busy professionals.",
    "Get reminders for timely billing."
  ],
  "value_props": [
    "Manual data entry support for accuracy.",
    "Basic reporting to track your finances.",
    "User-friendly design for clinic staff.",
    "Reminders to keep your billing on track.",
    "Simple tracking for patient invoices."
  ],
  "feature_bullets": [
    "Manual entry support tailored for clinics.",
    "Basic reporting features for financial insights.",
    "User-friendly interface for quick access.",
    "Timely reminders for invoice follow-ups.",
    "Easily track patient billing workflows."
  ],
  "cta_variants": [
    "Start simplifying your billing today.",
    "Get started with manual-first tracking.",
    "Try our easy-to-use billing tool.",
    "Join clinics enhancing their workflows.",
    "Experience efficient invoice management."
  ]
}
