{
  "taglines": [
    "Smart carrier choices for logistics coordinators.",
    "Cut shipping costs with informed decisions.",
    "Efficient workflows for logistics coordinators.",
    "Track shipments, save money.",
    "Manual insights for better carrier assignments."
  ],
  "hero_headlines": [
    "Optimize Your Shipping Costs Today.",
    "Empower Logistics Coordinators with Smart Choices.",
    "Say Goodbye to High Shipping Costs.",
    "Streamline Your Shipping Process.",
    "Transform Your Carrier Assignments."
  ],
  "hero_subheads": [
    "For logistics coordinators managing 50\u2013100 shipments/month.",
    "Make informed decisions on carrier assignments.",
    "Reduce budget overruns with precise tracking.",
    "Manual entry made simple for logistics coordinators.",
    "Achieve cost savings without the guesswork."
  ],
  "value_props": [
    "Manual tracking for accurate carrier performance.",
    "Cost analysis tailored for logistics coordinators.",
    "Simple invoice entry for seamless processing.",
    "Empower your decisions with data-driven insights.",
    "Streamlined workflows for managing shipments."
  ],
  "feature_bullets": [
    "Shipping cost analysis tool for logistics coordinators.",
    "Track carrier performance to ensure efficiency.",
    "Manual invoice entry form for easy management.",
    "Identify cost-saving carrier options effortlessly.",
    "Reminders for timely shipment tracking."
  ],
  "cta_variants": [
    "Start saving on shipping costs.",
    "Get started with smarter logistics.",
    "Try our manual-first tracking today.",
    "Optimize your shipments now.",
    "Join logistics coordinators in reducing costs."
  ]
}
