{
  "taglines": [
    "Track invoices manually, reduce errors.",
    "Simplify vendor invoice management.",
    "Stay on top of your payments.",
    "Effortless invoice entry for managers.",
    "Clear visibility for procurement tasks."
  ],
  "hero_headlines": [
    "Streamline your invoice tracking.",
    "Manual workflows made easy.",
    "Empower procurement managers today.",
    "Cut down on cash flow gaps.",
    "Transform your invoice management."
  ],
  "hero_subheads": [
    "For procurement managers handling 10-50 invoices/month.",
    "Say goodbye to tedious manual reconciliation.",
    "Gain control over vendor invoices effortlessly.",
    "Achieve accurate tracking with ease.",
    "Stay organized with simple reminders."
  ],
  "value_props": [
    "Manual entry forms tailored for procurement managers.",
    "User-friendly dashboard for tracking discrepancies.",
    "Weekly summary emails for better oversight.",
    "Reduce time spent on manual reconciliation.",
    "Improve cash flow management for your business."
  ],
  "feature_bullets": [
    "Weekly email reports to keep procurement managers informed.",
    "Dashboard designed for easy tracking of vendor invoices.",
    "Manual invoice entry forms to suit your workflow.",
    "Set reminders to avoid late payments.",
    "Track discrepancies without spreadsheets."
  ],
  "cta_variants": [
    "Start tracking your invoices today.",
    "Get started with manual tracking.",
    "Join fellow procurement managers now.",
    "Simplify your invoice process.",
    "Take control of your vendor invoices."
  ]
}
