{
  "taglines": [
    "Streamline your invoice tracking.",
    "Precision for project controllers.",
    "Manual-first tracking for accuracy.",
    "Budget alignment made easy.",
    "Clear insights for your invoices."
  ],
  "hero_headlines": [
    "Control your invoices with confidence.",
    "Accuracy in every entry.",
    "Simplify your budget tracking.",
    "Stay on top of vendor invoices.",
    "Reconcile without the hassle."
  ],
  "hero_subheads": [
    "For construction project controllers managing invoices.",
    "Ensure accurate reconciliation every time.",
    "Manual entry that supports your workflow.",
    "Track budgets and invoices seamlessly.",
    "Empower your financial oversight."
  ],
  "value_props": [
    "Manual invoice entry tailored for controllers.",
    "Budget tracking that fits your projects.",
    "Discrepancy reporting for informed decisions.",
    "Designed for construction project controllers.",
    "Enhance cash flow visibility today."
  ],
  "feature_bullets": [
    "Manual invoice entry for precise tracking.",
    "Budget tracking aligned with project goals.",
    "Easy reporting of discrepancies.",
    "User-friendly for construction project controllers.",
    "Focused on reducing cash flow gaps."
  ],
  "cta_variants": [
    "Start tracking your invoices now.",
    "Get started with manual entry today.",
    "Discover budget tracking features.",
    "Join other project controllers today.",
    "Request a demo for your team."
  ]
}
