{
  "schema_version": "1.0.0",
  "who": "Etsy sellers processing 10\u201320 invoices/month",
  "offer": "For Etsy sellers processing 10\u201320 invoices/month, delayed invoicing causes cash flow gaps. We streamline invoicing and payment tracking instead of manual invoicing and tracking through spreadsheets.",
  "problem": "Cash flow gaps due to delayed invoicing and payment tracking.",
  "channels_free": [
    "Post in Reddit communities for Etsy sellers",
    "Indie Hackers discussions on similar workflows",
    "DM outreach to Etsy sellers with demo video",
    "Community forums where Etsy sellers share tools"
  ],
  "try_it": "Let users try invoice generation on 1-3 items",
  "pay": "unknown with a clear upgrade path",
  "cheap_execution_checklist": [
    "1-page landing page with clear CTA",
    "Short demo video showing manual workflow",
    "Collect 10 interviews from target users",
    "Offer early-access onboarding for first users",
    "Post weekly updates in relevant communities"
  ],
  "automation_simplification_ideas": [
    "Save common inputs as templates",
    "Default reminder schedule presets",
    "CSV import for existing data",
    "One-click export of simple reports",
    "Simplify onboarding steps"
  ]
}
