{
  "idea_text": "System that extracts and consolidates utility bills for property managers and sends monthly summaries.",
  "scores": {
    "pricing_power": 90,
    "user_count": 70,
    "automation": 90,
    "market_clarity": 55,
    "competition_inverse": 55
  },
  "overlay_score": 78,
  "arr_score": 79.0,
  "verdict": "KEEP",
  "verdict_timestamp": "2026-04-02T19:37:33.388412",
  "verdict_source": "overlay_score",
  "arr_verdict": "HOLD",
  "arr_scored_at": "2026-04-02T19:37:33.442116",
  "hold_reason": "arr_70_89"
}