{
  "idea_text": "A dashboard that summarizes key financial metrics like cash flow, profitability, and tax planning for small business owners.",
  "scores": {
    "pricing_power": 70,
    "user_count": 70,
    "automation": 90,
    "market_clarity": 90,
    "competition_inverse": 55
  },
  "overlay_score": 76,
  "arr_score": 75.0,
  "verdict": "KEEP",
  "verdict_timestamp": "2026-03-27T18:55:12.370523",
  "verdict_source": "overlay_score",
  "arr_verdict": "HOLD",
  "arr_scored_at": "2026-03-27T18:55:12.401395",
  "hold_reason": "arr_70_89"
}