{
  "taglines": [
    "Track equipment usage manually.",
    "Simplify project management for contractors.",
    "Efficient tracking for busy contractors.",
    "Stay on top of multiple projects.",
    "Maximize equipment utilization."
  ],
  "hero_headlines": [
    "Manage your projects with ease.",
    "Stay organized across 15 projects.",
    "Track equipment usage simply.",
    "Efficient tools for contractors.",
    "Never miss a usage threshold."
  ],
  "hero_subheads": [
    "Manual entry made straightforward.",
    "Basic reporting at your fingertips.",
    "Get notified before you underutilize.",
    "Keep track without spreadsheets.",
    "Streamline your project oversight."
  ],
  "value_props": [
    "Manual entry tailored for contractors.",
    "Basic dashboard for quick insights.",
    "Email alerts for usage limits.",
    "Focus on managing projects, not spreadsheets.",
    "Ensure every piece of equipment is used."
  ],
  "feature_bullets": [
    "Manual entry of equipment usage for clarity.",
    "Basic reporting dashboard for quick reviews.",
    "Email notifications to avoid underutilization.",
    "Designed for contractors managing multiple projects.",
    "Simplified tracking for busy contractors."
  ],
  "cta_variants": [
    "Start tracking your equipment today.",
    "Get your free trial now.",
    "Join contractors simplifying their workflow.",
    "Discover better project management.",
    "Sign up for efficient tracking."
  ]
}
