{
  "taglines": [
    "Track shifts easily, HR managers.",
    "Simplify compliance for restaurant HR.",
    "Manual tracking made simple.",
    "Shift compliance, no spreadsheets.",
    "Empower HR managers with clarity."
  ],
  "hero_headlines": [
    "Streamline shift compliance tracking.",
    "Say goodbye to scheduling conflicts.",
    "Manual entry made efficient.",
    "HR managers, simplify your workflow.",
    "Manage shifts with confidence."
  ],
  "hero_subheads": [
    "A user-friendly tool for HR managers.",
    "Track exceptions without the hassle.",
    "No more confusion over shifts.",
    "Stay compliant with ease.",
    "Your manual entry partner in HR."
  ],
  "value_props": [
    "User-friendly dashboard for HR managers.",
    "Manual entry for shift exceptions.",
    "Eliminate scheduling conflicts.",
    "Stay compliant without spreadsheets.",
    "Efficient tracking for HR managers."
  ],
  "feature_bullets": [
    "Manual entry for shift exceptions.",
    "Dashboard tailored for HR managers.",
    "Simple tracking of compliance issues.",
    "Quick manual invoice entry form.",
    "Real-time updates for HR managers."
  ],
  "cta_variants": [
    "Start tracking shifts today.",
    "Get started with manual entry.",
    "Simplify your HR workflow now.",
    "Join other HR managers today.",
    "Take control of your shift compliance."
  ]
}
