{
  "taglines": [
    "Simplify your invoicing process.",
    "Effortless invoice tracking for law firms.",
    "Streamlined invoicing for billing admins.",
    "Manual-first workflows for accurate billing.",
    "Stay on top of vendor invoices."
  ],
  "hero_headlines": [
    "Invoicing Made Easy for Billing Administrators.",
    "Efficient Invoice Processing for Law Firms.",
    "Transform Your Manual Invoicing Workflow.",
    "Say Goodbye to Invoicing Errors.",
    "Take Control of Your Invoice Tracking."
  ],
  "hero_subheads": [
    "Manual entry is a thing of the past.",
    "Enhance cash flow with simple tracking.",
    "Customize invoices to fit your needs.",
    "Review before you send for peace of mind.",
    "Easily import time entries for accurate billing."
  ],
  "value_props": [
    "Manual review option for billing accuracy.",
    "Customizable invoice templates for law firms.",
    "Time entry imports save valuable time.",
    "Reduce errors in your billing process.",
    "Streamlined workflows for billing administrators."
  ],
  "feature_bullets": [
    "Import time entries with ease.",
    "Customize invoices to match your brand.",
    "Review invoices manually before sending.",
    "Track invoice payments effortlessly.",
    "Stay organized with simple reminders."
  ],
  "cta_variants": [
    "Start simplifying your invoicing today.",
    "Get started with manual-first workflows.",
    "Try our tool for better invoice tracking.",
    "Sign up for efficient billing processes.",
    "Discover how to streamline your invoicing."
  ]
}
