{
  "taglines": [
    "Simplify cash flow for small firms",
    "Manual tracking made easy",
    "Categorize with confidence",
    "Streamline your invoicing process",
    "Cash flow clarity for small firms"
  ],
  "hero_headlines": [
    "Transform Your Cash Flow Tracking",
    "Effortless Categorization for Small Firms",
    "Say Goodbye to Manual Errors",
    "Cash Flow Insights at Your Fingertips",
    "Easy Tracking for Busy Accountants"
  ],
  "hero_subheads": [
    "Manual entry made simple for small accounting firms.",
    "Custom categories tailored to your needs.",
    "Export reports without the hassle.",
    "Stay on top of your cash flow effortlessly.",
    "Designed for firms processing 5-15 invoices monthly."
  ],
  "value_props": [
    "Manual data entry for precise tracking.",
    "Customizable categories for better clarity.",
    "Export cash flow reports easily.",
    "Avoid cash flow gaps with accurate tracking.",
    "Designed for small accounting firms' workflows."
  ],
  "feature_bullets": [
    "Manual entry for every transaction.",
    "Categorize expenses and income easily.",
    "Generate reports without spreadsheets.",
    "Tailored for small firms handling 5-15 invoices.",
    "Clear cash flow insights for informed decisions."
  ],
  "cta_variants": [
    "Start tracking your cash flow today.",
    "Get started with manual categorization.",
    "Try our tool for small accounting firms.",
    "See how easy cash flow can be.",
    "Join other small firms simplifying their tracking."
  ]
}
