{
  "taglines": [
    "Track expenses, save time.",
    "Simple expense overview for finance managers.",
    "Stay on budget with clear insights.",
    "Manage invoices without the hassle.",
    "Visibility into spending for finance managers."
  ],
  "hero_headlines": [
    "Control Your Subscription Spending.",
    "Easy Expense Tracking for Finance Managers.",
    "Gain Clarity on Monthly Expenses.",
    "Stay Ahead of Overspending.",
    "Effortless Invoice Management for Finance Teams."
  ],
  "hero_subheads": [
    "Finance managers can now track expenses with ease.",
    "Get alerts on unusual charges and save cash.",
    "A dashboard designed for finance managers.",
    "Simplify your monthly expense reports.",
    "No more surprises in your subscription costs."
  ],
  "value_props": [
    "Finance managers reduce cash flow gaps.",
    "Stay informed with monthly expense reports.",
    "Identify unusual charges quickly.",
    "User-friendly dashboard tailored for finance managers.",
    "Manual tracking made simple and effective."
  ],
  "feature_bullets": [
    "Generate monthly expense reports effortlessly.",
    "Flag unusual charges for finance managers.",
    "User-friendly dashboard for quick insights.",
    "Track all subscriptions in one place.",
    "Receive reminders for upcoming payments."
  ],
  "cta_variants": [
    "Start tracking expenses today.",
    "Get your finance dashboard now.",
    "Sign up for better expense management.",
    "Take control of your subscriptions.",
    "Join finance managers who save money."
  ]
}
