{
  "taglines": [
    "Track vehicle maintenance manually.",
    "Simplify fleet oversight.",
    "Manage shipments efficiently.",
    "Stay ahead of breakdowns.",
    "Ensure vehicle readiness."
  ],
  "hero_headlines": [
    "For logistics managers: simplify maintenance tracking.",
    "Take control of fleet management.",
    "Efficient tracking for busy logistics managers.",
    "Stay on top of vehicle upkeep.",
    "Eliminate unexpected vehicle breakdowns."
  ],
  "hero_subheads": [
    "Manual entry made easy for logistics managers.",
    "Streamline your fleet's maintenance schedule.",
    "Custom reports for informed decisions.",
    "No more surprises on the road.",
    "Keep your shipments moving smoothly."
  ],
  "value_props": [
    "Manual tracking tailored for logistics managers.",
    "Easily schedule vehicle maintenance.",
    "Generate custom reports for better insights.",
    "Stay proactive with reminders.",
    "Simplify your workflow with straightforward tools."
  ],
  "feature_bullets": [
    "Track vehicle usage effortlessly.",
    "Schedule maintenance with a few clicks.",
    "Create reports that matter to logistics managers.",
    "Receive reminders for upcoming maintenance.",
    "Manage all shipments in one place."
  ],
  "cta_variants": [
    "Start tracking manually today.",
    "Get started with our fleet management tool.",
    "Sign up for streamlined vehicle maintenance.",
    "Join logistics managers optimizing their workflows.",
    "Request a demo for better tracking."
  ]
}
