{
  "schema_version": "1.0.0",
  "who": "insurance brokers managing 5\u201315 policies/month",
  "offer": "For insurance brokers processing 5\u201315 policies/month, missed renewal alerts cause client dissatisfaction. We provide timely renewal alerts instead of manual tracking through spreadsheets or paper files.",
  "problem": "Difficulty in tracking policy renewals and coverage details.",
  "channels_free": [
    "Post in Reddit communities for insurance brokers",
    "Engage in Indie Hackers discussions on workflows",
    "DM outreach to 20-50 insurance brokers with demo",
    "Share insights in community forums for brokers"
  ],
  "try_it": "Let users try policy cataloging and renewal alerts on 1-3 items",
  "pay": "unknown with a clear upgrade path",
  "cheap_execution_checklist": [
    "Create a landing page with a clear CTA",
    "Produce a short demo video of the workflow",
    "Conduct 10 interviews with target users",
    "Offer early-access onboarding for first 10 users",
    "Share weekly progress updates in relevant communities"
  ],
  "automation_simplification_ideas": [
    "Save common inputs as templates for reuse",
    "Set default reminder schedules for renewals",
    "Allow CSV import for existing policy data",
    "Enable one-click export of simple reports",
    "Streamline onboarding process with fewer steps"
  ]
}
