{
  "taglines": [
    "Keep HR on track with Gusto.",
    "Simplify employee enrollment for HR.",
    "Never miss a deadline again.",
    "HR made easy with manual reminders.",
    "Empower HR operations with simple tracking."
  ],
  "hero_headlines": [
    "Stay Ahead of Employee Enrollment Deadlines.",
    "Effortless Tracking for HR Operations.",
    "Your Partner in Employee Management.",
    "Timely Reminders for HR Success.",
    "Streamlined Enrollment for Small HR Teams."
  ],
  "hero_subheads": [
    "Manual-first workflows to enhance HR efficiency.",
    "No more missed deadlines with simple tracking.",
    "Keep your team informed and engaged.",
    "Transform your HR operations with Gusto.",
    "Focused on HR needs for small businesses."
  ],
  "value_props": [
    "Weekly reminders to keep HR organized.",
    "Dashboard for easy deadline tracking.",
    "Real-time updates on employee enrollment status.",
    "Designed for small HR teams using Gusto.",
    "Manual entry that enhances accuracy and accountability."
  ],
  "feature_bullets": [
    "Receive weekly notifications for upcoming deadlines.",
    "Visual dashboard for tracking enrollment progress.",
    "Instant updates on employee enrollment status.",
    "Tailored for HR operations in small companies.",
    "Simple interface for manual tracking of tasks."
  ],
  "cta_variants": [
    "Start tracking with Gusto today.",
    "Get timely reminders for your HR team.",
    "Sign up for better HR management.",
    "Join us and simplify your HR operations.",
    "Experience hassle-free employee enrollment."
  ]
}
