{
  "taglines": [
    "Streamline inspections for property managers.",
    "Simple tracking for busy property managers.",
    "Effortless reporting for property managers.",
    "Quick inspections, happy tenants.",
    "Manual entry made easy for property managers."
  ],
  "hero_headlines": [
    "Speed Up Your Inspection Process.",
    "Reduce Delays in Reporting Today.",
    "Simplify Inspections for Property Managers.",
    "Enhance Tenant Satisfaction with Faster Reports.",
    "Transform Your Inspection Workflow."
  ],
  "hero_subheads": [
    "Manual-first workflows for property managers.",
    "Say goodbye to delays in inspection reporting.",
    "Empower property managers with easy tracking.",
    "Efficient manual entry for your inspections.",
    "Keep tenants happy with timely reports."
  ],
  "value_props": [
    "Digital checklists for seamless inspections.",
    "Manual invoice entry tailored for property managers.",
    "Manage vendor lists effortlessly.",
    "Reduce tenant dissatisfaction with quick reports.",
    "Simplify your inspection workflow manually."
  ],
  "feature_bullets": [
    "Digital checklists designed for property managers.",
    "Manual entry forms for accurate invoicing.",
    "Vendor list management for easy access.",
    "Track inspections without delays.",
    "Ensure timely reporting for tenant satisfaction."
  ],
  "cta_variants": [
    "Start your inspection journey now.",
    "Get started with simple tracking today.",
    "Sign up for hassle-free inspections.",
    "Join property managers improving their workflow.",
    "Try our manual-first inspection tool."
  ]
}
