{
  "taglines": [
    "Simplify commission data entry.",
    "Streamline payroll processes.",
    "Effortless commission tracking.",
    "Reduce payroll delays.",
    "Precision for sales operations."
  ],
  "hero_headlines": [
    "For Sales Operations Managers: Make Data Entry Simple.",
    "Transform Your Commission Reporting.",
    "Say Goodbye to Payroll Delays.",
    "Empower Your Commission Management.",
    "Manual Work Made Easy for Sales Ops."
  ],
  "hero_subheads": [
    "Designed for Sales Operations Managers handling 10-20 reports monthly.",
    "Eliminate errors in payroll formats.",
    "Track commissions without the hassle.",
    "Focus on sales, not data entry.",
    "Your manual-first workflow partner."
  ],
  "value_props": [
    "User-friendly interface for easy data input.",
    "Export to payroll formats with a click.",
    "Basic error-checking for reliable data.",
    "Tailored for Sales Operations Managers' needs.",
    "Minimize time spent on commission reports."
  ],
  "feature_bullets": [
    "Intuitive data input for Sales Operations Managers.",
    "Quick export to common payroll formats.",
    "Error-checking to enhance data accuracy.",
    "Designed for 10-20 commission reports monthly.",
    "Manual-first approach to streamline workflows."
  ],
  "cta_variants": [
    "Start simplifying your commission process.",
    "Try it for your sales operations today.",
    "Get started with manual tracking.",
    "See how easy payroll can be.",
    "Join other Sales Operations Managers now."
  ]
}
