{
  "taglines": [
    "Stay compliant with ease.",
    "Never miss a renewal again.",
    "Track licenses simply.",
    "Your compliance partner.",
    "Manage renewals effortlessly."
  ],
  "hero_headlines": [
    "Simplify License Management for Administrators.",
    "Effortless Tracking for Insurance Agencies.",
    "Stay Ahead of Renewal Deadlines.",
    "Compliance Made Simple for Administrators.",
    "Reliable Reminders for License Renewals."
  ],
  "hero_subheads": [
    "Manual entry and customizable reminders at your fingertips.",
    "Track your licenses without the stress.",
    "Focused on compliance for agency administrators.",
    "Simple tools for busy insurance administrators.",
    "Manage renewals with confidence and clarity."
  ],
  "value_props": [
    "Manual entry for precise license tracking.",
    "Customizable reminders tailored for administrators.",
    "Dashboard view to monitor upcoming renewals.",
    "Reduce compliance risks with timely alerts.",
    "Designed for insurance agency administrators managing multiple licenses."
  ],
  "feature_bullets": [
    "Manual entry to ensure accurate license details.",
    "Set reminders that fit your workflow.",
    "Dashboard for a clear view of renewals.",
    "Designed for administrators handling 5-15 licenses.",
    "Easy tracking to avoid compliance issues."
  ],
  "cta_variants": [
    "Start tracking your licenses today.",
    "Get started with simple reminders.",
    "Sign up for easy compliance management.",
    "Try our dashboard for better tracking.",
    "Join now and simplify your license renewals."
  ]
}
