{
  "taglines": [
    "Streamline billing for consulting agencies.",
    "Simplified invoicing for busy consultants.",
    "Effortless billing for consulting agencies.",
    "Clear billing, smooth cash flow.",
    "Precision billing for consulting agencies."
  ],
  "hero_headlines": [
    "Say goodbye to billing errors, consulting agencies!",
    "Consulting agencies: Master your invoicing.",
    "Transform your billing process, consulting agencies.",
    "Consulting agencies, reclaim your cash flow.",
    "Billing made easy for consulting agencies."
  ],
  "hero_subheads": [
    "Manual entry for accurate billing records.",
    "Track your time without the hassle.",
    "Simplify your invoices, boost your cash flow.",
    "Consulting agencies, manage your invoices simply.",
    "Stay on top of your billing with ease."
  ],
  "value_props": [
    "Manual entry ensures accuracy for consulting agencies.",
    "Track project time effectively for better billing.",
    "Easily manage client invoices for cash flow.",
    "Consulting agencies can reduce billing errors.",
    "Stay organized with manual billing processes."
  ],
  "feature_bullets": [
    "Manual entry for client billing records.",
    "Track project time manually for precise invoicing.",
    "Simple manual invoice entry form.",
    "Consulting agencies can customize billing entries.",
    "Access billing history easily for consulting agencies."
  ],
  "cta_variants": [
    "Start tracking your invoices today.",
    "Get started with manual billing now.",
    "Simplify your billing process today.",
    "Join consulting agencies mastering their invoices.",
    "Take control of your billing workflow now."
  ]
}
