{
  "idea_text": "A service that monitors property maintenance schedules, alerts the property manager when tasks are due, and coordinates with vendors to schedule and complete the work.",
  "scores": {
    "pricing_power": 55,
    "user_count": 70,
    "automation": 90,
    "market_clarity": 70,
    "competition_inverse": 55
  },
  "overlay_score": 69,
  "arr_score": 68.0,
  "verdict": "KEEP",
  "verdict_timestamp": "2026-04-02T19:25:40.899017",
  "verdict_source": "overlay_score",
  "arr_verdict": "EXCLUDE",
  "arr_scored_at": "2026-04-02T19:25:40.946884"
}