{
  "idea_text": "System that reconciles sales commissions with CRM data and provides weekly alerts to sales ops managers.",
  "scores": {
    "pricing_power": 50,
    "user_count": 55,
    "automation": 90,
    "market_clarity": 90,
    "competition_inverse": 55
  },
  "overlay_score": 66,
  "arr_score": 64.0,
  "verdict": "KEEP",
  "verdict_timestamp": "2026-04-02T19:25:40.889090",
  "verdict_source": "overlay_score",
  "arr_verdict": "EXCLUDE",
  "arr_scored_at": "2026-04-02T19:25:40.939350"
}