{
  "taglines": [
    "Streamline scheduling for HR teams",
    "Effortless time-off management",
    "Simplify invoice tracking for HR teams",
    "Visual scheduling made easy",
    "Empower HR teams with manual workflows"
  ],
  "hero_headlines": [
    "Efficient Scheduling for HR Teams",
    "Transform Time-Off Management",
    "Simplify Your Scheduling Process",
    "Manual Tracking, Made Simple",
    "Stay on Schedule with Ease"
  ],
  "hero_subheads": [
    "For HR teams managing 5-15 employees",
    "Eliminate missed deadlines with clear tracking",
    "Visualize your team's availability effortlessly",
    "Manual entry for precise invoice management",
    "Keep your HR processes organized and efficient"
  ],
  "value_props": [
    "Tailored for HR teams in small agencies",
    "Manual-first approach for accurate scheduling",
    "Visual calendar for easy time-off tracking",
    "Streamlined invoice entry for HR teams",
    "Reduce errors with simple manual workflows"
  ],
  "feature_bullets": [
    "Simple time-off request form for HR teams",
    "Visual scheduling calendar for easy access",
    "Manual invoice entry form to avoid confusion",
    "Clear reminders for time-off approvals",
    "Efficient tracking for HR teams managing schedules"
  ],
  "cta_variants": [
    "Start simplifying your scheduling today",
    "Get organized with our manual tracking tool",
    "Try our visual scheduling calendar now",
    "Request a demo for HR teams",
    "Join HR teams already streamlining their processes"
  ]
}
