{
  "taglines": [
    "Simplify utility bill tracking.",
    "Effortless summaries for property managers.",
    "Stay on top of your utility bills.",
    "Track utility costs with ease.",
    "Your manual tracking partner."
  ],
  "hero_headlines": [
    "Streamline Your Utility Bill Process.",
    "No More Cash Flow Gaps.",
    "Simplify Your Utility Bill Management.",
    "Efficient Tracking for Property Managers.",
    "Take Control of Utility Costs."
  ],
  "hero_subheads": [
    "Manual tracking made simple for property managers.",
    "Get timely summaries without the hassle.",
    "Focus on properties, not paperwork.",
    "Transform how you manage utility bills.",
    "Stay organized with easy tracking."
  ],
  "value_props": [
    "Property managers save time on bill summaries.",
    "Stay informed with email notifications.",
    "Easily input utility bill details.",
    "Get clear insights into utility costs.",
    "Property managers can track multiple properties effortlessly."
  ],
  "feature_bullets": [
    "Receive monthly email summaries.",
    "Input utility bill details manually.",
    "Basic reporting for property managers.",
    "Track utility bills across multiple properties.",
    "Stay organized with reminders for due bills."
  ],
  "cta_variants": [
    "Start simplifying your tracking today.",
    "Get started with easy bill management.",
    "Join property managers who trust us.",
    "Try our tool for hassle-free tracking.",
    "Take the first step towards better tracking."
  ]
}
