{
  "taglines": [
    "Streamline your travel expense reports.",
    "Simplify manual invoice entry.",
    "Quick approvals for accounting firms.",
    "Effortless tracking for travel expenses.",
    "Reduce delays in reimbursements."
  ],
  "hero_headlines": [
    "Manage travel expenses with ease.",
    "Say goodbye to manual delays.",
    "Fast-track your expense approvals.",
    "Transform your expense reporting process.",
    "Empower your accounting team today."
  ],
  "hero_subheads": [
    "For accounting firms handling 10-20 reports monthly.",
    "Eliminate late reimbursements with simple tracking.",
    "Manual entry made straightforward.",
    "Get real-time insights into expenses.",
    "Streamline approvals without spreadsheets."
  ],
  "value_props": [
    "Save time with easy manual entry.",
    "Accurate tracking for every expense.",
    "Timely reimbursements for your clients.",
    "Real-time dashboards for accounting firms.",
    "Simplified workflows for busy accountants."
  ],
  "feature_bullets": [
    "Expense report templates tailored for accountants.",
    "Real-time reporting dashboards for quick insights.",
    "Manual invoice entry forms for accuracy.",
    "Custom reminders for timely approvals.",
    "User-friendly interface for all accounting firms."
  ],
  "cta_variants": [
    "Start managing expenses today.",
    "Get your free trial now.",
    "Join other accounting firms simplifying expenses.",
    "See how easy expense tracking can be.",
    "Request a demo for your accounting team."
  ]
}
