{
  "taglines": [
    "Streamline vehicle maintenance for fleet managers.",
    "Stay on top of vehicle health effortlessly.",
    "Simplify maintenance scheduling for your fleet.",
    "Reliable reminders for fleet operations managers.",
    "Effortless tracking for logistics vehicle upkeep."
  ],
  "hero_headlines": [
    "Never miss a maintenance check again.",
    "Keep your fleet running smoothly.",
    "Maintenance reminders made easy for fleet managers.",
    "Transform how you manage vehicle upkeep.",
    "Stay ahead of breakdowns with simple tracking."
  ],
  "hero_subheads": [
    "Manual entry, customizable schedules, and timely reminders.",
    "Empower your fleet operations with better scheduling.",
    "Say goodbye to unexpected breakdowns.",
    "Track vehicle health with ease and precision.",
    "Manage 10-50 vehicles without the hassle."
  ],
  "value_props": [
    "Manual entry ensures accurate vehicle details.",
    "Customizable schedules fit your fleet's needs.",
    "Email reminders keep maintenance on your radar.",
    "Reduce breakdowns with consistent tracking.",
    "Designed for fleet managers handling 10-50 vehicles."
  ],
  "feature_bullets": [
    "Easily input vehicle information manually.",
    "Set maintenance schedules that work for your fleet.",
    "Receive email reminders for upcoming service.",
    "Track vehicle performance without spreadsheets.",
    "Ideal for fleet operations managers in logistics."
  ],
  "cta_variants": [
    "Start managing your fleet better today.",
    "Get your maintenance reminders now.",
    "Sign up for hassle-free vehicle tracking.",
    "Take control of your fleet's maintenance.",
    "Join fleet managers who trust our reminders."
  ]
}
